lambda_thread_pool/LambdaThreadPool.py
lambda_thread_pool/__init__.py
lambda_thread_pool-0.0.2.dist-info/METADATA
lambda_thread_pool-0.0.2.dist-info/WHEEL
lambda_thread_pool-0.0.2.dist-info/top_level.txt
lambda_thread_pool-0.0.2.dist-info/RECORD
