Metadata-Version: 2.1
Name: lambda-thread-pool
Version: 0.0.2
Summary: AWS Lambda thread pool (lambda-thread-pool) uses multiprocessing.Pipe instead of multiprocessing.Queue. It provides the ability to perform parallel execution within the AWS lambda Python execution environment.
Home-page: https://github.com/kankou-aliaksei/lambda-thread-pool
Author: Aliaksei Kankou
Author-email: aliaksei.kankou@gmail.com
Project-URL: Bug Tracker, https://github.com/kankou-aliaksei/lambda-thread-pool/issues
Requires-Python: >3.7.0
